educat_log/__init__.py
educat_log/admin.py
educat_log/exceptions.py
educat_log/manager.py
educat_log/middleware.py
educat_log/models.py
educat_log/signals.py
educat_log/template_utils.py
educat_log/utils.py
educat_log/management/__init__.py
educat_log/management/commands/__init__.py
educat_log/management/commands/clean_duplicate_history.py
educat_log/management/commands/clean_old_history.py
educat_log/management/commands/populate_history.py
educat_log/registry_tests/__init__.py
educat_log/registry_tests/models.py
educat_log/registry_tests/tests.py
educat_log/registry_tests/migration_test_app/__init__.py
educat_log/registry_tests/migration_test_app/models.py
educat_log/registry_tests/migration_test_app/migrations/0001_initial.py
educat_log/registry_tests/migration_test_app/migrations/0002_historicalmodelwithcustomattrforeignkey_modelwithcustomattrforeignkey.py
educat_log/registry_tests/migration_test_app/migrations/0003_alter_historicalmodelwithcustomattrforeignkey_options_and_more.py
educat_log/registry_tests/migration_test_app/migrations/0004_history_date_indexing.py
educat_log/registry_tests/migration_test_app/migrations/0005_historicalmodelwithcustomattronetoonefield_modelwithcustomattronetoonefield.py
educat_log/registry_tests/migration_test_app/migrations/0006_alter_historicalmodelwithcustomattronetoonefield_options_and_more.py
educat_log/registry_tests/migration_test_app/migrations/0007_alter_historicalmodelwithcustomattrforeignkey_options_and_more.py
educat_log/registry_tests/migration_test_app/migrations/__init__.py
educat_log/templatetags/__init__.py
educat_log/templatetags/getattributes.py
educat_log/templatetags/simple_history_admin_list.py
educat_log/templatetags/simple_history_compat.py
educat_log/tests/__init__.py
educat_log/tests/admin.py
educat_log/tests/models.py
educat_log/tests/other_admin.py
educat_log/tests/urls.py
educat_log/tests/view.py
educat_log/tests/custom_user/__init__.py
educat_log/tests/custom_user/admin.py
educat_simple_log-0.2.0.dist-info/AUTHORS.rst
educat_simple_log-0.2.0.dist-info/LICENSE.txt
educat_simple_log-0.2.0.dist-info/METADATA
educat_simple_log-0.2.0.dist-info/WHEEL
educat_simple_log-0.2.0.dist-info/top_level.txt
educat_simple_log-0.2.0.dist-info/RECORD
