Metadata-Version: 2.1
Name: educat-simple-log
Version: 0.2.0
Summary: Modifed version of django-simple-history
Home-page: https://github.com/devthz/django-simple-history
Author: Thiago Henrique
Author-email: thiago@educat.app.br
License: UNKNOWN
Platform: UNKNOWN
Classifier: Programming Language :: Python :: 3
Classifier: License :: OSI Approved :: MIT License
Classifier: Operating System :: OS Independent
Requires-Python: >=3.6
Requires-Dist: django >=2.2
